mnemosynecore/__init__.py
mnemosynecore/config.py
mnemosynecore/mattermost.py
mnemosynecore/superset.py
mnemosynecore/vault.py
mnemosynecore/vertica.py
mnemosynecore/warnings.py
mnemosynecoretest-0.0.2.dist-info/METADATA
mnemosynecoretest-0.0.2.dist-info/WHEEL
mnemosynecoretest-0.0.2.dist-info/top_level.txt
mnemosynecoretest-0.0.2.dist-info/RECORD
